setup.cfg
setup.py
es_ouroboros.egg-info/PKG-INFO
es_ouroboros.egg-info/SOURCES.txt
es_ouroboros.egg-info/dependency_links.txt
es_ouroboros.egg-info/entry_points.txt
es_ouroboros.egg-info/requires.txt
es_ouroboros.egg-info/top_level.txt
ouroboros/__init__.py
ouroboros/cli.py
ouroboros/client.py
test/test_acl_equality.py
test/test_default_stream_update.py
test/test_stream_creation.py
test/test_stream_update.py
test/test_user_creation.py
test/test_user_deletion.py
test/test_user_fetching.py
test/test_user_update.py