Metadata-Version: 1.0
Name: es-ouroboros
Version: 0.4
Summary: Management CLI and library for EventStore
Home-page: https://github.com/madedotcom/ouroboros/
Author: Bob Gregory
Author-email: pathogenix@gmail.com
License: UNKNOWN
Keywords: eventstore,cli,management
Platform: UNKNOWN
